ukbb_loaders/__init__.py
ukbb_loaders/files/__init__.py
ukbb_loaders/files/lookups/__init__.py
ukbb_loaders/files/lookups/ehr_diagnosis_icd10.parquet
ukbb_loaders/files/lookups/ehr_diagnosis_icd9.parquet
ukbb_loaders/files/lookups/ehr_diagnosis_phecodes.parquet
ukbb_loaders/files/lookups/ehr_diagnosis_read2.parquet
ukbb_loaders/files/lookups/ehr_diagnosis_read3.parquet
ukbb_loaders/files/lookups/ehr_procedures_opcs3.parquet
ukbb_loaders/files/lookups/ehr_procedures_opcs4.parquet
ukbb_loaders/files/lookups/parent_lookup.parquet
ukbb_loaders/files/lookups/ukbiobank_assessment_centre_fields.parquet
ukbb_loaders/files/lookups/ukbiobank_diagnosis_self_reported_20002.parquet
ukbb_loaders/files/lookups/ukbiobank_ethnicity.parquet
ukbb_loaders/files/lookups/ukbiobank_medications_self_reported_20003.parquet
ukbb_loaders/files/lookups/ukbiobank_metabolomics_fields.parquet
ukbb_loaders/files/lookups/ukbiobank_procedures_self_reported_20004.parquet
ukbb_loaders/files/mappers/__init__.py
ukbb_loaders/files/mappers/ac_to_opcs4.parquet
ukbb_loaders/files/mappers/atc_child_to_parent.parquet
ukbb_loaders/files/mappers/icd10_to_mondo.parquet
ukbb_loaders/files/mappers/icd10_to_phecodes.parquet
ukbb_loaders/files/mappers/medications_to_atc.parquet
ukbb_loaders/files/mappers/mondo_to_icd10.parquet
ukbb_loaders/files/mappers/opcs3_to_opcs4.parquet
ukbb_loaders/files/mappers/readcode_to_icd10.parquet
ukbb_loaders/loaders/__init__.py
ukbb_loaders/loaders/load.py
ukbb_loaders/utilities/__init__.py
ukbb_loaders/utilities/util.py
ukbb_parser/__init__.py
ukbb_parser/update_data.py
ukbb_parser/updater/__init__.py
ukbb_parser/updater/derive_death.py
ukbb_parser/updater/derive_gp.py
ukbb_parser/updater/derive_hospital.py
ukbb_parser/updater/standardise_raw.py
ukbb_parser/updater/utils.py
ukbiobank_loaders-1.1.0.data/scripts/update_data.py
ukbiobank_loaders-1.1.0.dist-info/LICENSE
ukbiobank_loaders-1.1.0.dist-info/METADATA
ukbiobank_loaders-1.1.0.dist-info/WHEEL
ukbiobank_loaders-1.1.0.dist-info/top_level.txt
ukbiobank_loaders-1.1.0.dist-info/RECORD
