Metadata-Version: 2.1
Name: ukbiobank-loaders
Version: 1.1.0
Summary: Utility package for handling UK Biobank data
Home-page: https://github.com/BenevolentAI/ukbiobank-loaders
Author: BenevolentAI
Author-email: ukbiobank.loaders@benevolent.ai
License: MIT
Classifier: Intended Audience :: Science/Research
Classifier: Intended Audience :: Developers
Classifier: License :: OSI Approved :: MIT License
Classifier: Programming Language :: Python
Classifier: Programming Language :: Python :: 3.7
Classifier: Programming Language :: Python :: 3.8
Classifier: Programming Language :: Python :: 3.9
Classifier: Topic :: Software Development
Classifier: Topic :: Scientific/Engineering
Classifier: Topic :: Scientific/Engineering :: Bio-Informatics
Requires-Python: >3.7
License-File: LICENSE
Requires-Dist: boto3 (==1.17.106)
Requires-Dist: numpy (>=1.21.6)
Requires-Dist: pandas (>=1.3.5)
Requires-Dist: pyarrow
Requires-Dist: s3fs (==2021.11.0)
